sqladmin/__init__.py
sqladmin/_menu.py
sqladmin/_queries.py
sqladmin/_types.py
sqladmin/_validators.py
sqladmin/ajax.py
sqladmin/application.py
sqladmin/authentication.py
sqladmin/exceptions.py
sqladmin/fields.py
sqladmin/formatters.py
sqladmin/forms.py
sqladmin/helpers.py
sqladmin/models.py
sqladmin/pagination.py
sqladmin/py.typed
sqladmin/templating.py
sqladmin/widgets.py
sqladmin/statics/css/flatpickr.min.css
sqladmin/statics/css/fontawesome.min.css
sqladmin/statics/css/main.css
sqladmin/statics/css/select2.min.css
sqladmin/statics/css/tabler-icons.min.css
sqladmin/statics/css/tabler-icons.min.css.map
sqladmin/statics/css/tabler.min.css
sqladmin/statics/js/bootstrap.min.js
sqladmin/statics/js/flatpickr.min.js
sqladmin/statics/js/jquery.min.js
sqladmin/statics/js/main.js
sqladmin/statics/js/popper.min.js
sqladmin/statics/js/select2.full.min.js
sqladmin/statics/js/tabler.min.js
sqladmin/statics/webfonts/fa-brands-400.woff2
sqladmin/statics/webfonts/fa-regular-400.woff2
sqladmin/statics/webfonts/fa-solid-900.woff2
sqladmin/statics/webfonts/tabler-icons.woff2
sqladmin/templates/sqladmin/_macros.html
sqladmin/templates/sqladmin/base.html
sqladmin/templates/sqladmin/create.html
sqladmin/templates/sqladmin/details.html
sqladmin/templates/sqladmin/edit.html
sqladmin/templates/sqladmin/error.html
sqladmin/templates/sqladmin/index.html
sqladmin/templates/sqladmin/layout.html
sqladmin/templates/sqladmin/list.html
sqladmin/templates/sqladmin/login.html
sqladmin/templates/sqladmin/modals/delete.html
sqladmin/templates/sqladmin/modals/details_action_confirmation.html
sqladmin/templates/sqladmin/modals/list_action_confirmation.html
sqladmin-0.20.0.dist-info/METADATA
sqladmin-0.20.0.dist-info/WHEEL
sqladmin-0.20.0.dist-info/licenses/LICENSE.md
sqladmin-0.20.0.dist-info/RECORD
