Metadata-Version: 2.3
Name: sqladmin
Version: 0.20.0
Summary: SQLAlchemy admin for FastAPI and Starlette
Project-URL: Documentation, https://aminalaee.dev/sqladmin
Project-URL: Issues, https://github.com/aminalaee/sqladmin/issues
Project-URL: Source, https://github.com/aminalaee/sqladmin
Author-email: Amin Alaee <me@aminalaee.dev>
License-Expression: BSD-3-Clause
License-File: LICENSE.md
Keywords: admin,fastapi,sqlalchemy,starlette
Classifier: Development Status :: 4 - Beta
Classifier: Environment :: Web Environment
Classifier: Intended Audience :: Developers
Classifier: License :: OSI Approved :: BSD License
Classifier: Operating System :: OS Independent
Classifier: Programming Language :: Python
Classifier: Programming Language :: Python :: 3.8
Classifier: Programming Language :: Python :: 3.9
Classifier: Programming Language :: Python :: 3.10
Classifier: Programming Language :: Python :: 3.11
Classifier: Programming Language :: Python :: 3.12
Classifier: Topic :: Internet :: WWW/HTTP
Requires-Python: >=3.8
Requires-Dist: jinja2
Requires-Dist: python-multipart
Requires-Dist: sqlalchemy>=1.4
Requires-Dist: starlette
Requires-Dist: wtforms<3.2,>=3.1
Provides-Extra: full
Requires-Dist: itsdangerous; extra == 'full'
